asgi_cors_strawberry/__init__.py
asgi_cors_strawberry/middleware.py
asgi_cors_strawberry-0.1.0.dist-info/LICENSE
asgi_cors_strawberry-0.1.0.dist-info/METADATA
asgi_cors_strawberry-0.1.0.dist-info/WHEEL
asgi_cors_strawberry-0.1.0.dist-info/top_level.txt
asgi_cors_strawberry-0.1.0.dist-info/RECORD
