Metadata-Version: 2.1
Name: asgi-cors-strawberry
Version: 0.1.0
Summary: ASGI middleware for CORS, especially for using strawberry[channels]
Home-page: https://github.com/hot666666/asgi-cors-strawberry
Author: Hot666666
License: Apache License, Version 2.0
License-File: LICENSE
